{"nodes": [{"id": "d_v5_board_app_src_v5_command_program_c", "label": "v5_command_program.c", "file_type": "code", "source_file": "v5_command_program.c", "source_location": "L1"}, {"id": "d_v5_board_app_src_v5_command_program_v5_program_controller_init", "label": "v5_program_controller_init()", "file_type": "code", "source_file": "v5_command_program.c", "source_location": "L6", "_callable": true}, {"id": "v5programcontroller", "label": "V5ProgramController", "file_type": "code", "source_file": "", "source_location": "", "origin_file": "D:\\v5\\board\\app\\src\\v5_command_program.c"}, {"id": "d_v5_board_app_src_v5_command_program_v5_program_controller_destroy", "label": "v5_program_controller_destroy()", "file_type": "code", "source_file": "v5_command_program.c", "source_location": "L15", "_callable": true}, {"id": "d_v5_board_app_src_v5_command_program_v5_command_program_open", "label": "v5_command_program_open()", "file_type": "code", "source_file": "v5_command_program.c", "source_location": "L25", "_callable": true}, {"id": "v5programopenresult", "label": "V5ProgramOpenResult", "file_type": "code", "source_file": "", "source_location": "", "origin_file": "D:\\v5\\board\\app\\src\\v5_command_program.c"}, {"id": "d_v5_board_app_src_v5_command_program_v5_command_program_delete", "label": "v5_command_program_delete()", "file_type": "code", "source_file": "v5_command_program.c", "source_location": "L46", "_callable": true}, {"id": "v5programdeleteresult", "label": "V5ProgramDeleteResult", "file_type": "code", "source_file": "", "source_location": "", "origin_file": "D:\\v5\\board\\app\\src\\v5_command_program.c"}, {"id": "d_v5_board_app_src_v5_command_program_v5_program_controller_runtime", "label": "v5_program_controller_runtime()", "file_type": "code", "source_file": "v5_command_program.c", "source_location": "L66", "_callable": true}, {"id": "v5programruntime", "label": "V5ProgramRuntime", "file_type": "code", "source_file": "", "source_location": "", "origin_file": "D:\\v5\\board\\app\\src\\v5_command_program.c"}], "edges": [{"source": "d_v5_board_app_src_v5_command_program_c", "target": "d_v5_board_app_src_v5_command_program_h", "relation": "imports", "context": "import", "confidence": "EXTRACTED", "source_file": "v5_command_program.c", "source_location": "L1", "weight": 1.0}, {"source": "d_v5_board_app_src_v5_command_program_c", "target": "malloc", "relation": "imports", "context": "import", "confidence": "EXTRACTED", "source_file": "v5_command_program.c", "source_location": "L3", "weight": 1.0}, {"source": "d_v5_board_app_src_v5_command_program_c", "target": "string", "relation": "imports", "context": "import", "confidence": "EXTRACTED", "source_file": "v5_command_program.c", "source_location": "L4", "weight": 1.0}, {"source": "d_v5_board_app_src_v5_command_program_c", "target": "d_v5_board_app_src_v5_command_program_v5_program_controller_init", "relation": "contains", "confidence": "EXTRACTED", "source_file": "v5_command_program.c", "source_location": "L6", "weight": 1.0}, {"source": "d_v5_board_app_src_v5_command_program_v5_program_controller_init", "target": "v5programcontroller", "relation": "references", "confidence": "EXTRACTED", "source_file": "v5_command_program.c", "source_location": "L6", "weight": 1.0, "context": "parameter_type"}, {"source": "d_v5_board_app_src_v5_command_program_c", "target": "d_v5_board_app_src_v5_command_program_v5_program_controller_destroy", "relation": "contains", "confidence": "EXTRACTED", "source_file": "v5_command_program.c", "source_location": "L15", "weight": 1.0}, {"source": "d_v5_board_app_src_v5_command_program_v5_program_controller_destroy", "target": "v5programcontroller", "relation": "references", "confidence": "EXTRACTED", "source_file": "v5_command_program.c", "source_location": "L15", "weight": 1.0, "context": "parameter_type"}, {"source": "d_v5_board_app_src_v5_command_program_c", "target": "d_v5_board_app_src_v5_command_program_v5_command_program_open", "relation": "contains", "confidence": "EXTRACTED", "source_file": "v5_command_program.c", "source_location": "L25", "weight": 1.0}, {"source": "d_v5_board_app_src_v5_command_program_v5_command_program_open", "target": "v5programcontroller", "relation": "references", "confidence": "EXTRACTED", "source_file": "v5_command_program.c", "source_location": "L25", "weight": 1.0, "context": "parameter_type"}, {"source": "d_v5_board_app_src_v5_command_program_v5_command_program_open", "target": "v5programopenresult", "relation": "references", "confidence": "EXTRACTED", "source_file": "v5_command_program.c", "source_location": "L25", "weight": 1.0, "context": "parameter_type"}, {"source": "d_v5_board_app_src_v5_command_program_c", "target": "d_v5_board_app_src_v5_command_program_v5_command_program_delete", "relation": "contains", "confidence": "EXTRACTED", "source_file": "v5_command_program.c", "source_location": "L46", "weight": 1.0}, {"source": "d_v5_board_app_src_v5_command_program_v5_command_program_delete", "target": "v5programcontroller", "relation": "references", "confidence": "EXTRACTED", "source_file": "v5_command_program.c", "source_location": "L46", "weight": 1.0, "context": "parameter_type"}, {"source": "d_v5_board_app_src_v5_command_program_v5_command_program_delete", "target": "v5programdeleteresult", "relation": "references", "confidence": "EXTRACTED", "source_file": "v5_command_program.c", "source_location": "L46", "weight": 1.0, "context": "parameter_type"}, {"source": "d_v5_board_app_src_v5_command_program_c", "target": "d_v5_board_app_src_v5_command_program_v5_program_controller_runtime", "relation": "contains", "confidence": "EXTRACTED", "source_file": "v5_command_program.c", "source_location": "L66", "weight": 1.0}, {"source": "d_v5_board_app_src_v5_command_program_v5_program_controller_runtime", "target": "v5programruntime", "relation": "references", "confidence": "EXTRACTED", "source_file": "v5_command_program.c", "source_location": "L66", "weight": 1.0, "context": "return_type"}, {"source": "d_v5_board_app_src_v5_command_program_v5_program_controller_runtime", "target": "v5programcontroller", "relation": "references", "confidence": "EXTRACTED", "source_file": "v5_command_program.c", "source_location": "L66", "weight": 1.0, "context": "parameter_type"}], "raw_calls": [{"caller_nid": "d_v5_board_app_src_v5_command_program_v5_program_controller_init", "callee": "memset", "is_member_call": false, "source_file": "v5_command_program.c", "source_location": "L11", "receiver": null}, {"caller_nid": "d_v5_board_app_src_v5_command_program_v5_program_controller_init", "callee": "v5_program_runtime_init", "is_member_call": false, "source_file": "v5_command_program.c", "source_location": "L12", "receiver": null}, {"caller_nid": "d_v5_board_app_src_v5_command_program_v5_program_controller_destroy", "callee": "v5_program_runtime_destroy", "is_member_call": false, "source_file": "v5_command_program.c", "source_location": "L20", "receiver": null}, {"caller_nid": "d_v5_board_app_src_v5_command_program_v5_program_controller_destroy", "callee": "malloc_trim", "is_member_call": false, "source_file": "v5_command_program.c", "source_location": "L21", "receiver": null}, {"caller_nid": "d_v5_board_app_src_v5_command_program_v5_program_controller_destroy", "callee": "memset", "is_member_call": false, "source_file": "v5_command_program.c", "source_location": "L22", "receiver": null}, {"caller_nid": "d_v5_board_app_src_v5_command_program_v5_command_program_open", "callee": "memset", "is_member_call": false, "source_file": "v5_command_program.c", "source_location": "L34", "receiver": null}, {"caller_nid": "d_v5_board_app_src_v5_command_program_v5_command_program_open", "callee": "v5_program_runtime_open_file", "is_member_call": false, "source_file": "v5_command_program.c", "source_location": "L39", "receiver": null}, {"caller_nid": "d_v5_board_app_src_v5_command_program_v5_command_program_delete", "callee": "memset", "is_member_call": false, "source_file": "v5_command_program.c", "source_location": "L54", "receiver": null}, {"caller_nid": "d_v5_board_app_src_v5_command_program_v5_command_program_delete", "callee": "v5_program_runtime_delete_file", "is_member_call": false, "source_file": "v5_command_program.c", "source_location": "L59", "receiver": null}, {"caller_nid": "d_v5_board_app_src_v5_command_program_v5_command_program_delete", "callee": "memset", "is_member_call": false, "source_file": "v5_command_program.c", "source_location": "L61", "receiver": null}]}